holowan/GetHoloWANParameter.py
holowan/HoloWAN.py
holowan/__init__.py
holowan/myUtils/JsonUtil.py
holowan/myUtils/MyUtil.py
holowan/myUtils/XmlUtil.py
holowan/myUtils/__init__.py
holowan/resources/HoloWAN.ini
holowan/resources/HoloWAN_parameter.xml
holowan/resources/__init__.py
holowan/resources/path_config.xml
holowan/resources/path_crud.xml
holowan/resources/recorder_config.xml
holowan-1980.dist-info/LICENSE
holowan-1980.dist-info/METADATA
holowan-1980.dist-info/WHEEL
holowan-1980.dist-info/top_level.txt
holowan-1980.dist-info/RECORD
