Metadata-Version: 2.1
Name: holowan
Version: 1980
Summary: This is a Python SDK for HoloWAN
Home-page: UNKNOWN
Author: chanyulin
License: UNKNOWN
Platform: UNKNOWN
License-File: LICENSE
